autodoc_ai/ast_handler.py
autodoc_ai/cli.py
autodoc_ai/config.py
autodoc_ai/generators.py
autodoc_ai/llm_services.py
autodoc_ai/transformers.py
autodoc_ai/utils.py
autodoc_ai_paudelnirajan-0.1.4.dist-info/METADATA
autodoc_ai_paudelnirajan-0.1.4.dist-info/WHEEL
autodoc_ai_paudelnirajan-0.1.4.dist-info/entry_points.txt
autodoc_ai_paudelnirajan-0.1.4.dist-info/top_level.txt
autodoc_ai_paudelnirajan-0.1.4.dist-info/RECORD
